apiscope/__init__.py
apiscope/cli.py
apiscope/commands/__init__.py
apiscope/commands/describe.py
apiscope/commands/init.py
apiscope/commands/list.py
apiscope/commands/search.py
apiscope/core/__init__.py
apiscope/core/config.py
apiscope/core/output.py
apiscope/core/parser.py
llm_api_scope-0.2.0.dist-info/licenses/LICENSE
llm_api_scope-0.2.0.dist-info/METADATA
llm_api_scope-0.2.0.dist-info/WHEEL
llm_api_scope-0.2.0.dist-info/entry_points.txt
llm_api_scope-0.2.0.dist-info/top_level.txt
llm_api_scope-0.2.0.dist-info/RECORD
