Metadata-Version: 2.4
Name: llm-api-scope
Version: 0.2.0
Summary: Default template for PDM package
Author-email: D7x7z49 <85430783+D7x7z49@users.noreply.github.com>
License: MIT
Requires-Python: <4.0,>=3.12
License-File: LICENSE
Requires-Dist: click>=8.3.1
Requires-Dist: openapi-core>=0.22.0
Requires-Dist: httpx>=0.28.1
Dynamic: license-file
